<?xml version='1.0' encoding='utf-8'?>





<img x="-32" y="-40" w="282" h="178" />
<offsets>
	<floor x="141" y="89" />
	<cloak x="141" y="89" />
</offsets>
<weaponMounts>
	<mount x="171" y="105" rotate="false" mirror="false" gib="1" slide="up" />
	<mount x="201" y="106" rotate="false" mirror="false" gib="1" slide="up" />
	<mount x="228" y="105" rotate="false" mirror="false" gib="3" slide="up" />
</weaponMounts>
<explosion><gib1><velocity min="0.12847614221934608" max="0.4282538073978203" /><direction min="213" max="229" /><angular min="-0.8393979933110367" max="0.8393979933110367" /><x>122</x><y>73</y></gib1><gib2><velocity min="0.1" max="0.22539261227903457" /><direction min="127" max="143" /><angular min="-0.6359674208144795" max="0.6359674208144795" /><x>72</x><y>49</y></gib2><gib3><velocity min="0.20587559088212942" max="0.6862519696070981" /><direction min="255" max="271" /><angular min="-0.5638642381449089" max="0.5638642381449089" /><x>192</x><y>27</y></gib3><gib4><velocity min="0.3225502263272298" max="1.075167421090766" /><direction min="59" max="75" /><angular min="-0.8433265330613224" max="0.8433265330613224" /><x>4</x><y>1</y></gib4><gib5><velocity min="0.37405674443582776" max="1.2468558147860926" /><direction min="104" max="120" /><angular min="-0.9568954248366012" max="0.9568954248366012" /><x>3</x><y>84</y></gib5></explosion>

