<?xml version='1.0' encoding='utf-8'?>



<img x="-129" y="-102" w="548" h="556" />
<offsets>
	<floor x="124" y="96" />
	<cloak x="-8" y="-8" />
</offsets>
<weaponMounts>
	<mount x="515" y="345" rotate="true" mirror="true" gib="2" slide="up" />
	<mount x="518" y="214" rotate="true" mirror="false" gib="3" slide="down" />
	<mount x="431" y="153" rotate="true" mirror="true" gib="3" slide="up" />
	<mount x="428" y="404" rotate="true" mirror="false" gib="2" slide="down" />
</weaponMounts>
<explosion>
	<gib1><velocity min="0.16934676410124688" max="0.5644892136708229" /><direction min="177" max="193" /><angular min="-0.7936650169314925" max="0.7936650169314925" /><x>195</x><y>260</y></gib1><gib2><velocity min="0.26814776461443074" max="0.8938258820481024" /><direction min="234" max="250" /><angular min="-0.8985006845708267" max="0.8985006845708267" /><x>321</x><y>258</y></gib2><gib3><velocity min="0.14869204892349058" max="0.495640163078302" /><direction min="303" max="319" /><angular min="-0.5488743630655206" max="0.5488743630655206" /><x>251</x><y>38</y></gib3><gib4><velocity min="0.1743883229916324" max="0.581294409972108" /><direction min="35" max="51" /><angular min="-0.5501627673020868" max="0.5501627673020868" /><x>0</x><y>0</y></gib4><gib5><velocity min="0.3387102951885657" max="1.129034317295219" /><direction min="119" max="135" /><angular min="-0.9911315581579069" max="0.9911315581579069" /><x>0</x><y>301</y></gib5></explosion>

