<?xml version='1.0' encoding='utf-8'?>






<img x="-83" y="-33" w="643" h="391" />
<offsets>
	<floor x="77" y="27" />
	<cloak x="2" y="1" />
</offsets>
<weaponMounts>
	<mount x="364" y="17" rotate="true" mirror="true" gib="3" slide="up" />
	<mount x="526" y="96" rotate="true" mirror="true" gib="2" slide="up" />
	<mount x="571" y="176" rotate="true" mirror="false" gib="2" slide="down" />
	<mount x="435" y="327" rotate="true" mirror="false" gib="1" slide="down" />
	<mount x="509" y="251" rotate="true" mirror="false" gib="2" slide="down" />
</weaponMounts>
<explosion><gib1><velocity min="0.1" max="0.3329746812601487" /><direction min="221" max="237" /><angular min="-0.8638349776665194" max="0.8638349776665194" /><x>256</x><y>153</y></gib1><gib2><velocity min="0.19996595203261328" max="0.6665531734420442" /><direction min="279" max="295" /><angular min="-0.6446487179487178" max="0.6446487179487178" /><x>384</x><y>18</y></gib2><gib3><velocity min="0.11283160484941135" max="0.37610534949803787" /><direction min="1" max="17" /><angular min="-0.7853676060423499" max="0.7853676060423499" /><x>189</x><y>16</y></gib3><gib4><velocity min="0.16914717150484743" max="0.5638239050161581" /><direction min="69" max="85" /><angular min="-0.547161733615222" max="0.547161733615222" /><x>28</x><y>16</y></gib4><gib5><velocity min="0.3007100858660979" max="1.002366952886993" /><direction min="114" max="130" /><angular min="-1.0165141800958817" max="1.0165141800958817" /><x>66</x><y>202</y></gib5></explosion>
