<?xml version='1.0' encoding='utf-8'?>




<img x="-154" y="-83" w="548" h="556" />
<offsets>
	<floor x="147" y="76" />
	<cloak x="-8" y="-8" />
</offsets>
<weaponMounts>
	<mount x="434" y="158" rotate="true" mirror="true" gib="3" slide="up" />
	<mount x="434" y="398" rotate="true" mirror="false" gib="1" slide="down" />
</weaponMounts>
<explosion><gib1><velocity min="0.24385866033627263" max="0.8128622011209088" /><direction min="232" max="248" /><angular min="-0.8377124901806755" max="0.8377124901806755" /><x>308</x><y>260</y></gib1><gib2><velocity min="0.16924860318886734" max="0.5641620106295578" /><direction min="178" max="194" /><angular min="-0.7953520286396182" max="0.7953520286396182" /><x>195</x><y>259</y></gib2><gib3><velocity min="0.13759976195835735" max="0.4586658731945245" /><direction min="301" max="317" /><angular min="-0.531251650185568" max="0.531251650185568" /><x>248</x><y>43</y></gib3><gib4><velocity min="0.1762703538672336" max="0.5875678462241121" /><direction min="35" max="51" /><angular min="-0.5541365065343343" max="0.5541365065343343" /><x>0</x><y>0</y></gib4><gib5><velocity min="0.329865346867572" max="1.09955115622524" /><direction min="119" max="135" /><angular min="-0.9727337407643892" max="0.9727337407643892" /><x>0</x><y>301</y></gib5></explosion>
